Workbook

Sheet Summary
A1: LiquidPay - Manual Test Case Tracker
A3: Manual QA test suite for LiquidPay digital wallet using the provided execution-report template.
A5: Workbook Controls
A6: Default Status | B6: Not Run
A7: Default Priority | B7: High
A8: Portfolio Owner | B8: Ramon Tan Jr
A9: Primary Domain | B9: FinTech / Digital Wallet QA
A11: Module Coverage
A12: Module | B12: Sheet Name | C12: Total Cases | D12: High Priority | E12: Negative Cases | F12: Automation Candidates
A13: Registration & Login | B13: Registration_Login | C13: =COUNTA(Registration_Login!A5:A200) -> 11 | D13: =COUNTIF(Registration_Login!H:H,"High")+COUNTIF(Registration_Login!H:H,"Critical") -> 0 | E13: =COUNTIF(Registration_Login!I:I,"Negative")+COUNTIF(Registration_Login!I:I,"Security")+COUNTIF(Registration_Login!I:I,"Compliance")+COUNTIF(Registration_Login!I:I,"Audit") -> 0 | F13: =COUNTIF(Registration_Login!J:J,"Yes") -> 0
A14: Wallet & Account | B14: Wallet_Account | C14: =COUNTA(Wallet_Account!A5:A200) -> 8 | D14: =COUNTIF(Wallet_Account!H:H,"High")+COUNTIF(Wallet_Account!H:H,"Critical") -> 0 | E14: =COUNTIF(Wallet_Account!I:I,"Negative")+COUNTIF(Wallet_Account!I:I,"Security")+COUNTIF(Wallet_Account!I:I,"Compliance")+COUNTIF(Wallet_Account!I:I,"Audit") -> 0 | F14: =COUNTIF(Wallet_Account!J:J,"Yes") -> 0
A15: QR Payment | B15: QR_Payment | C15: =COUNTA(QR_Payment!A5:A200) -> 12 | D15: =COUNTIF(QR_Payment!H:H,"High")+COUNTIF(QR_Payment!H:H,"Critical") -> 0 | E15: =COUNTIF(QR_Payment!I:I,"Negative")+COUNTIF(QR_Payment!I:I,"Security")+COUNTIF(QR_Payment!I:I,"Compliance")+COUNTIF(QR_Payment!I:I,"Audit") -> 0 | F15: =COUNTIF(QR_Payment!J:J,"Yes") -> 0
A16: Transfer & Remittance | B16: Transfer_Remittance | C16: =COUNTA(Transfer_Remittance!A5:A200) -> 10 | D16: =COUNTIF(Transfer_Remittance!H:H,"High")+COUNTIF(Transfer_Remittance!H:H,"Critical") -> 0 | E16: =COUNTIF(Transfer_Remittance!I:I,"Negative")+COUNTIF(Transfer_Remittance!I:I,"Security")+COUNTIF(Transfer_Remittance!I:I,"Compliance")+COUNTIF(Transfer_Remittance!I:I,"Audit") -> 0 | F16: =COUNTIF(Transfer_Remittance!J:J,"Yes") -> 0
A17: History & Disputes | B17: History_Disputes | C17: =COUNTA(History_Disputes!A5:A200) -> 10 | D17: =COUNTIF(History_Disputes!H:H,"High")+COUNTIF(History_Disputes!H:H,"Critical") -> 0 | E17: =COUNTIF(History_Disputes!I:I,"Negative")+COUNTIF(History_Disputes!I:I,"Security")+COUNTIF(History_Disputes!I:I,"Compliance")+COUNTIF(History_Disputes!I:I,"Audit") -> 0 | F17: =COUNTIF(History_Disputes!J:J,"Yes") -> 0
A18: Security & Compliance | B18: Security_Compliance | C18: =COUNTA(Security_Compliance!A5:A200) -> 9 | D18: =COUNTIF(Security_Compliance!H:H,"High")+COUNTIF(Security_Compliance!H:H,"Critical") -> 0 | E18: =COUNTIF(Security_Compliance!I:I,"Negative")+COUNTIF(Security_Compliance!I:I,"Security")+COUNTIF(Security_Compliance!I:I,"Compliance")+COUNTIF(Security_Compliance!I:I,"Audit") -> 0 | F18: =COUNTIF(Security_Compliance!J:J,"Yes") -> 0
A19: End-to-End | B19: End_to_End | C19: =COUNTA(End_to_End!A5:A200) -> 6 | D19: =COUNTIF(End_to_End!H:H,"High")+COUNTIF(End_to_End!H:H,"Critical") -> 0 | E19: =COUNTIF(End_to_End!I:I,"Negative")+COUNTIF(End_to_End!I:I,"Security")+COUNTIF(End_to_End!I:I,"Compliance")+COUNTIF(End_to_End!I:I,"Audit") -> 0 | F19: =COUNTIF(End_to_End!J:J,"Yes") -> 0
A20: Total | C20: =SUM(C13:C19) -> 66 | D20: =SUM(D13:D19) -> 0 | E20: =SUM(E13:E19) -> 0 | F20: =SUM(F13:F19) -> 0
A21: Execution Status
A22: Status | B22: Count | D22: Execution KPI
A23: Not Run | B23: =COUNTIF(Registration_Login!K:K,A23)+COUNTIF(Wallet_Account!K:K,A23)+COUNTIF(QR_Payment!K:K,A23)+COUNTIF(Transfer_Remittance!K:K,A23)+COUNTIF(History_Disputes!K:K,A23)+COUNTIF(Security_Compliance!K:K,A23)+COUNTIF(End_to_End!K:K,A23) -> 0 | D23: Total Test Cases | E23: =SUM(B23:B26) -> 0
A24: Pass | B24: =COUNTIF(Registration_Login!K:K,A24)+COUNTIF(Wallet_Account!K:K,A24)+COUNTIF(QR_Payment!K:K,A24)+COUNTIF(Transfer_Remittance!K:K,A24)+COUNTIF(History_Disputes!K:K,A24)+COUNTIF(Security_Compliance!K:K,A24)+COUNTIF(End_to_End!K:K,A24) -> 0 | D24: Executed Cases | E24: =B24+B25+B26 -> 0
A25: Fail | B25: =COUNTIF(Registration_Login!K:K,A25)+COUNTIF(Wallet_Account!K:K,A25)+COUNTIF(QR_Payment!K:K,A25)+COUNTIF(Transfer_Remittance!K:K,A25)+COUNTIF(History_Disputes!K:K,A25)+COUNTIF(Security_Compliance!K:K,A25)+COUNTIF(End_to_End!K:K,A25) -> 0 | D25: Pass Rate | E25: =IF(E24=0,0,B24/E24) -> 0
A26: Blocked | B26: =COUNTIF(Registration_Login!K:K,A26)+COUNTIF(Wallet_Account!K:K,A26)+COUNTIF(QR_Payment!K:K,A26)+COUNTIF(Transfer_Remittance!K:K,A26)+COUNTIF(History_Disputes!K:K,A26)+COUNTIF(Security_Compliance!K:K,A26)+COUNTIF(End_to_End!K:K,A26) -> 0 | D26: Fail Rate | E26: =IF(E24=0,0,B25/E24) -> 0

Sheet Registration_Login
A1: Registration and Login Test Cases
A2: Update the Status column during execution. Summary KPIs and counts refresh automatically.
A4: TC_ID | B4: Module | C4: Scenario | D4: Acceptance Criteria (BDD) Given valid preconditions When scenario Then expected result is achieved | E4: Preconditions | F4: Steps | G4: Test Data | H4: Expected Result | I4: Priority | J4: Type | K4: Automation Candidate | L4: Status | M4: Notes
A5: TC-REG-001 | B5: Registration & Login | C5: Verify new user can register with valid required details | D5: Given valid preconditions When verify new user can register with valid required details Then expected result is achieved | E5: LiquidPay app is installed on a supported device | F5: 1. Open app 2. Tap Register 3. Enter valid mobile/email and required profile details 4. Submit registration | G5: Valid user profile data | H5: Registration succeeds and user proceeds to verification or home flow | I5: High | J5: Positive | K5: Yes | L5: Not Run | M5: Core onboarding smoke
A6: TC-REG-002 | B6: Registration & Login | C6: Verify mandatory registration fields are validated | D6: Given valid preconditions When verify mandatory registration fields are validated Then expected result is achieved | E6: Registration screen is open | F6: 1. Leave one or more required fields blank 2. Tap Submit/Register | G6: Blank required fields | H6: Validation messages appear and account is not created | I6: High | J6: Negative | K6: Yes | L6: Not Run | M6: Field-level validation
A7: TC-REG-003 | B7: Registration & Login | C7: Verify invalid mobile number or email format is rejected | D7: Given valid preconditions When verify invalid mobile number or email format is rejected Then expected result is achieved | E7: Registration screen is open | F7: 1. Enter invalid email/mobile format 2. Submit form | G7: Invalid email/mobile formats | H7: Inline validation is shown and submission is blocked | I7: High | J7: Negative | K7: Yes | L7: Not Run | M7: Input validation
A8: TC-REG-004 | B8: Registration & Login | C8: Verify duplicate registration using an existing account identifier is blocked | D8: Given valid preconditions When verify duplicate registration using an existing account identifier is blocked Then expected result is achieved | E8: Existing account already exists | F8: 1. Attempt registration using previously registered email/mobile 2. Submit | G8: Existing user identifier | H8: System prevents duplicate account creation and displays clear message | I8: High | J8: Negative | K8: Yes | L8: Not Run | M8: Duplicate prevention
A9: TC-REG-005 | B9: Registration & Login | C9: Verify underage applicant cannot complete registration | D9: Given valid preconditions When verify underage applicant cannot complete registration Then expected result is achieved | E9: Registration screen is open | F9: 1. Enter date of birth below minimum allowed age 2. Submit | G9: DOB below minimum age | H9: Registration is rejected due to age policy | I9: High | J9: Negative | K9: Yes | L9: Not Run | M9: Compliance validation
A10: TC-REG-006 | B10: Registration & Login | C10: Verify identity verification succeeds with valid user information | D10: Given valid preconditions When verify identity verification succeeds with valid user information Then expected result is achieved | E10: User is registered and verification step is available | F10: 1. Start identity verification 2. Complete with valid details 3. Submit | G10: Valid verification data | H10: Account is marked verified and eligible wallet functions become available | I10: Critical | J10: Positive | K10: Later | L10: Not Run | M10: KYC success path
A11: TC-REG-007 | B11: Registration & Login | C11: Verify verification failure or cancellation keeps user in unverified state | D11: Given valid preconditions When verify verification failure or cancellation keeps user in unverified state Then expected result is achieved | E11: Verification step is available | F11: 1. Start identity verification 2. Cancel flow or provide invalid details | G11: Cancelled flow / invalid verification data | H11: Verification remains incomplete and restricted actions stay blocked | I11: High | J11: Negative | K11: Later | L11: Not Run | M11: KYC failure path
A12: TC-LOG-001 | B12: Registration & Login | C12: Verify registered user can log in with valid credentials | D12: Given valid preconditions When verify registered user can log in with valid credentials Then expected result is achieved | E12: Existing active account exists | F12: 1. Open login 2. Enter valid credentials 3. Submit | G12: Valid credentials/OTP | H12: Login succeeds and wallet home screen loads | I12: High | J12: Positive | K12: Yes | L12: Not Run | M12: Core access path
A13: TC-LOG-002 | B13: Registration & Login | C13: Verify invalid credentials are rejected without exposing sensitive details | D13: Given valid preconditions When verify invalid credentials are rejected without exposing sensitive details Then expected result is achieved | E13: Login screen is open | F13: 1. Enter invalid password/PIN/OTP 2. Submit | G13: Invalid credentials | H13: Login fails with generic error message and no access is granted | I13: High | J13: Negative | K13: Yes | L13: Not Run | M13: Auth validation
A14: TC-LOG-003 | B14: Registration & Login | C14: Verify multiple failed login attempts trigger protective controls | D14: Given valid preconditions When verify multiple failed login attempts trigger protective controls Then expected result is achieved | E14: Login screen is open | F14: 1. Enter wrong credentials repeatedly 2. Observe response after threshold | G14: Repeated invalid attempts | H14: System enforces lockout, cooldown, or step-up verification per policy | I14: Critical | J14: Security | K14: Yes | L14: Not Run | M14: Brute-force control
A15: TC-LOG-004 | B15: Registration & Login | C15: Verify user can log out successfully | D15: Given valid preconditions When verify user can log out successfully Then expected result is achieved | E15: User is logged in | F15: 1. Open profile/menu 2. Tap Logout | G15: N/A | H15: User session is ended and login screen is shown | I15: Medium | J15: Positive | K15: Yes | L15: Not Run | M15: Basic session control

Sheet Wallet_Account
A1: Wallet and Account Test Cases
A2: Update the Status column during execution. Summary KPIs and counts refresh automatically.
A4: TC_ID | B4: Module | C4: Scenario | D4: Acceptance Criteria (BDD) Given valid preconditions When scenario Then expected result is achieved | E4: Preconditions | F4: Steps | G4: Test Data | H4: Expected Result | I4: Priority | J4: Type | K4: Automation Candidate | L4: Status | M4: Notes
A5: TC-WAL-001 | B5: Wallet & Account | C5: Verify wallet home displays current available balance | D5: Given valid preconditions When verify wallet home displays current available balance Then expected result is achieved | E5: Verified user is logged in | F5: 1. Open wallet home/dashboard 2. Review displayed balance | G5: Wallet with existing balance | H5: Available balance is displayed accurately | I5: High | J5: Positive | K5: Yes | L5: Not Run | M5: Primary wallet info
A6: TC-WAL-002 | B6: Wallet & Account | C6: Verify unverified user cannot access restricted wallet actions | D6: Given valid preconditions When verify unverified user cannot access restricted wallet actions Then expected result is achieved | E6: Unverified user is logged in | F6: 1. Attempt restricted action such as transfer or certain payment flow | G6: Unverified account | H6: Restricted action is blocked with verification guidance | I6: Critical | J6: Negative | K6: Yes | L6: Not Run | M6: Eligibility control
A7: TC-WAL-003 | B7: Wallet & Account | C7: Verify wallet profile details can be viewed without error | D7: Given valid preconditions When verify wallet profile details can be viewed without error Then expected result is achieved | E7: User is logged in | F7: 1. Open account/profile section 2. Review profile details | G7: Existing account | H7: Profile details load correctly | I7: Medium | J7: Positive | K7: Yes | L7: Not Run | M7: Profile read-only check
A8: TC-WAL-004 | B8: Wallet & Account | C8: Verify user can update editable profile information | D8: Given valid preconditions When verify user can update editable profile information Then expected result is achieved | E8: User is logged in and profile update is allowed | F8: 1. Open editable profile fields 2. Update allowed field(s) 3. Save changes | G8: Updated profile values | H8: Changes are saved successfully and reflected on reload | I8: Medium | J8: Positive | K8: Later | L8: Not Run | M8: Profile maintenance
A9: TC-WAL-005 | B9: Wallet & Account | C9: Verify invalid profile update data is rejected | D9: Given valid preconditions When verify invalid profile update data is rejected Then expected result is achieved | E9: Editable profile page is open | F9: 1. Enter invalid format in editable field 2. Save | G9: Invalid profile value | H9: Validation is shown and invalid changes are not saved | I9: Medium | J9: Negative | K9: Later | L9: Not Run | M9: Input validation
A10: TC-WAL-006 | B10: Wallet & Account | C10: Verify wallet remains usable after app relaunch | D10: Given valid preconditions When verify wallet remains usable after app relaunch Then expected result is achieved | E10: User is logged in | F10: 1. Close app 2. Relaunch app 3. Return to wallet | G10: Existing logged-in account | H10: Wallet data loads as expected according to session policy | I10: Medium | J10: Regression | K10: Yes | L10: Not Run | M10: State persistence
A11: TC-WAL-007 | B11: Wallet & Account | C11: Verify account freeze state is displayed clearly on wallet | D11: Given valid preconditions When verify account freeze state is displayed clearly on wallet Then expected result is achieved | E11: Frozen account exists | F11: 1. Log in to frozen account 2. Review wallet banners/messages | G11: Frozen account | H11: Freeze status and restrictions are clearly displayed | I11: High | J11: Negative | K11: Yes | L11: Not Run | M11: Compliance status display
A12: TC-WAL-008 | B12: Wallet & Account | C12: Verify frozen account cannot initiate transactions | D12: Given valid preconditions When verify frozen account cannot initiate transactions Then expected result is achieved | E12: Frozen account exists | F12: 1. Attempt QR payment or transfer | G12: Frozen account | H12: Transaction initiation is blocked consistently | I12: Critical | J12: Negative | K12: Yes | L12: Not Run | M12: Regulatory hold

Sheet QR_Payment
A1: QR Payment Test Cases
A2: Update the Status column during execution. Summary KPIs and counts refresh automatically.
A4: TC_ID | B4: Module | C4: Scenario | D4: Acceptance Criteria (BDD) Given valid preconditions When scenario Then expected result is achieved | E4: Preconditions | F4: Steps | G4: Test Data | H4: Expected Result | I4: Priority | J4: Type | K4: Automation Candidate | L4: Status | M4: Notes
A5: TC-QRP-001 | B5: QR Payment | C5: Verify verified user can complete successful local QR payment | D5: Given valid preconditions When verify verified user can complete successful local qr payment Then expected result is achieved | E5: Verified user with sufficient balance is logged in | F5: 1. Open Scan & Pay 2. Scan valid merchant QR 3. Confirm payment | G5: Supported local merchant QR | H5: Payment succeeds and confirmation is shown | I5: Critical | J5: Positive | K5: Yes | L5: Not Run | M5: Core business flow
A6: TC-QRP-002 | B6: QR Payment | C6: Verify payment detail screen shows merchant/reference and amount before confirmation | D6: Given valid preconditions When verify payment detail screen shows merchant/reference and amount before confirmation Then expected result is achieved | E6: User scans a supported QR | F6: 1. Scan valid QR 2. Review payment detail screen | G6: Valid QR | H6: Payment details are displayed accurately before user confirms | I6: High | J6: Positive | K6: Yes | L6: Not Run | M6: Pre-submit confirmation
A7: TC-QRP-003 | B7: QR Payment | C7: Verify invalid or unreadable QR code is rejected gracefully | D7: Given valid preconditions When verify invalid or unreadable qr code is rejected gracefully Then expected result is achieved | E7: Scan screen is open | F7: 1. Scan corrupted/unsupported QR | G7: Invalid/unsupported QR | H7: System shows clear error and no transaction is created | I7: High | J7: Negative | K7: Yes | L7: Not Run | M7: Unsupported input
A8: TC-QRP-004 | B8: QR Payment | C8: Verify expired QR code cannot be paid | D8: Given valid preconditions When verify expired qr code cannot be paid Then expected result is achieved | E8: Time-bound QR is available | F8: 1. Scan expired QR 2. Confirm payment if allowed | G8: Expired QR | H8: Payment is blocked with expired QR message | I8: High | J8: Negative | K8: Yes | L8: Not Run | M8: Time validity
A9: TC-QRP-005 | B9: QR Payment | C9: Verify payment is blocked when wallet balance is insufficient | D9: Given valid preconditions When verify payment is blocked when wallet balance is insufficient Then expected result is achieved | E9: Verified user has balance lower than transaction amount | F9: 1. Scan valid QR 2. Attempt payment | G9: Amount > available balance | H9: Payment fails with insufficient balance message and no debit occurs | I9: Critical | J9: Negative | K9: Yes | L9: Not Run | M9: Funds validation
A10: TC-QRP-006 | B10: QR Payment | C10: Verify duplicate payment tap does not create double charge | D10: Given valid preconditions When verify duplicate payment tap does not create double charge Then expected result is achieved | E10: Valid QR is scanned and submit button is available | F10: 1. Tap confirm multiple times rapidly | G10: Same QR and amount | H10: Only one transaction is processed and one confirmation is produced | I10: Critical | J10: Negative | K10: Yes | L10: Not Run | M10: Idempotency
A11: TC-QRP-007 | B11: QR Payment | C11: Verify user can cancel before final payment submission | D11: Given valid preconditions When verify user can cancel before final payment submission Then expected result is achieved | E11: Payment details are displayed | F11: 1. Tap Cancel/Back before confirm | G11: Valid QR | H11: No transaction is created and balance remains unchanged | I11: Medium | J11: Positive | K11: Yes | L11: Not Run | M11: Safe exit
A12: TC-QRP-008 | B12: QR Payment | C12: Verify network interruption during payment does not cause inconsistent wallet debit | D12: Given valid preconditions When verify network interruption during payment does not cause inconsistent wallet debit Then expected result is achieved | E12: Payment is in progress | F12: 1. Scan valid QR 2. Confirm payment 3. Interrupt network mid-process | G12: Intermittent network | H12: App handles pending/unknown status safely and prevents duplicate debit | I12: Critical | J12: Edge | K12: Later | L12: Not Run | M12: Timeout resilience
A13: TC-QRP-009 | B13: QR Payment | C13: Verify payment failure due to merchant/service decline is communicated correctly | D13: Given valid preconditions When verify payment failure due to merchant/service decline is communicated correctly Then expected result is achieved | E13: Supported QR flow is available with forced decline condition | F13: 1. Scan valid QR 2. Trigger decline response | G13: Merchant/system decline test data | H13: Payment fails with clear message and no balance deduction | I13: High | J13: Negative | K13: Later | L13: Not Run | M13: Downstream decline
A14: TC-QRP-010 | B14: QR Payment | C14: Verify successful cross-border QR payment is processed correctly | D14: Given valid preconditions When verify successful cross-border qr payment is processed correctly Then expected result is achieved | E14: Verified eligible user with sufficient balance is logged in | F14: 1. Scan supported overseas QR 2. Review payable amount 3. Confirm | G14: Supported overseas/cross-border QR | H14: Payment completes successfully and transaction is recorded accurately | I14: Critical | J14: Positive | K14: Later | L14: Not Run | M14: Cross-border payment
A15: TC-QRP-011 | B15: QR Payment | C15: Verify transaction record is created immediately after successful QR payment | D15: Given valid preconditions When verify transaction record is created immediately after successful qr payment Then expected result is achieved | E15: Successful QR payment has just completed | F15: 1. Complete successful payment 2. Open recent transactions | G15: Successful QR payment | H15: Latest payment appears with correct status, amount, merchant, and reference | I15: High | J15: Regression | K15: Yes | L15: Not Run | M15: History sync
A16: TC-QRP-012 | B16: QR Payment | C16: Verify unsupported currency or malformed amount from QR is handled safely | D16: Given valid preconditions When verify unsupported currency or malformed amount from qr is handled safely Then expected result is achieved | E16: Test QR with unsupported currency/malformed payload is available | F16: 1. Scan QR with invalid amount/currency payload | G16: Malformed QR payload | H16: System rejects payment and does not proceed to debit | I16: High | J16: Negative | K16: Later | L16: Not Run | M16: Data integrity

Sheet Transfer_Remittance
A1: Transfer and Remittance Test Cases
A2: Update the Status column during execution. Summary KPIs and counts refresh automatically.
A4: TC_ID | B4: Module | C4: Scenario | D4: Acceptance Criteria (BDD) Given valid preconditions When scenario Then expected result is achieved | E4: Preconditions | F4: Steps | G4: Test Data | H4: Expected Result | I4: Priority | J4: Type | K4: Automation Candidate | L4: Status | M4: Notes
A5: TC-XFR-001 | B5: Transfer & Remittance | C5: Verify successful transfer to valid recipient | D5: Given valid preconditions When verify successful transfer to valid recipient Then expected result is achieved | E5: Verified user with sufficient balance is logged in | F5: 1. Open Transfer 2. Enter/select valid recipient 3. Enter amount 4. Submit | G5: Valid recipient and amount | H5: Transfer succeeds and confirmation is shown | I5: Critical | J5: Positive | K5: Yes | L5: Not Run | M5: Core transfer flow
A6: TC-XFR-002 | B6: Transfer & Remittance | C6: Verify transfer summary shows recipient and amount before confirmation | D6: Given valid preconditions When verify transfer summary shows recipient and amount before confirmation Then expected result is achieved | E6: Transfer entry screen is open | F6: 1. Enter valid recipient and amount 2. Continue to summary | G6: Valid recipient and amount | H6: Confirmation screen displays correct recipient and transfer amount | I6: High | J6: Positive | K6: Yes | L6: Not Run | M6: Pre-submit review
A7: TC-XFR-003 | B7: Transfer & Remittance | C7: Verify invalid recipient identifier is rejected | D7: Given valid preconditions When verify invalid recipient identifier is rejected Then expected result is achieved | E7: Transfer entry screen is open | F7: 1. Enter invalid recipient ID/account 2. Submit | G7: Invalid recipient identifier | H7: Transfer is blocked with validation/error message | I7: High | J7: Negative | K7: Yes | L7: Not Run | M7: Recipient validation
A8: TC-XFR-004 | B8: Transfer & Remittance | C8: Verify insufficient balance blocks transfer | D8: Given valid preconditions When verify insufficient balance blocks transfer Then expected result is achieved | E8: Verified user has low balance | F8: 1. Enter valid recipient and amount exceeding available balance 2. Submit | G8: Amount > balance | H8: Transfer fails and no debit occurs | I8: Critical | J8: Negative | K8: Yes | L8: Not Run | M8: Funds validation
A9: TC-XFR-005 | B9: Transfer & Remittance | C9: Verify zero or negative transfer amount is rejected | D9: Given valid preconditions When verify zero or negative transfer amount is rejected Then expected result is achieved | E9: Transfer entry screen is open | F9: 1. Enter zero or negative amount 2. Submit | G9: 0 / negative amount | H9: Validation blocks submission | I9: Medium | J9: Negative | K9: Yes | L9: Not Run | M9: Amount validation
A10: TC-XFR-006 | B10: Transfer & Remittance | C10: Verify transfer amount above allowed limit is blocked | D10: Given valid preconditions When verify transfer amount above allowed limit is blocked Then expected result is achieved | E10: User is logged in | F10: 1. Enter valid recipient 2. Enter amount above configured limit 3. Submit | G10: Amount above transfer limit | H10: Transfer is rejected with limit message | I10: High | J10: Negative | K10: Yes | L10: Not Run | M10: Transaction limit
A11: TC-XFR-007 | B11: Transfer & Remittance | C11: Verify duplicate transfer retry does not post twice | D11: Given valid preconditions When verify duplicate transfer retry does not post twice Then expected result is achieved | E11: Initial transfer request is already submitted | F11: 1. Re-submit same transfer after delay/spinner 2. Check result | G11: Same recipient and amount | H11: Only one transfer is recorded | I11: Critical | J11: Negative | K11: Yes | L11: Not Run | M11: Idempotency
A12: TC-XFR-008 | B12: Transfer & Remittance | C12: Verify user can cancel transfer before final submission | D12: Given valid preconditions When verify user can cancel transfer before final submission Then expected result is achieved | E12: Transfer confirmation screen is open | F12: 1. Tap Cancel/Back | G12: Valid recipient and amount | H12: No transfer is created | I12: Medium | J12: Positive | K12: Yes | L12: Not Run | M12: Safe exit
A13: TC-XFR-009 | B13: Transfer & Remittance | C13: Verify timeout during transfer resolves to a consistent final state | D13: Given valid preconditions When verify timeout during transfer resolves to a consistent final state Then expected result is achieved | E13: Transfer request is in progress | F13: 1. Submit transfer 2. Simulate network timeout/interruption 3. Re-open history or refresh status | G13: Intermittent network | H13: Final status is accurate and only one financial outcome exists | I13: Critical | J13: Edge | K13: Later | L13: Not Run | M13: Resilience
A14: TC-XFR-010 | B14: Transfer & Remittance | C14: Verify cross-border transfer uses correct recipient rail details | D14: Given valid preconditions When verify cross-border transfer uses correct recipient rail details Then expected result is achieved | E14: Cross-border transfer option is available | F14: 1. Select supported rail/region 2. Enter recipient 3. Submit valid amount | G14: Supported cross-border recipient data | H14: Transfer succeeds and rail-specific details are recorded correctly | I14: Critical | J14: Positive | K14: Later | L14: Not Run | M14: Cross-border coverage

Sheet History_Disputes
A1: History and Disputes Test Cases
A2: Update the Status column during execution. Summary KPIs and counts refresh automatically.
A4: TC_ID | B4: Module | C4: Scenario | D4: Acceptance Criteria (BDD) Given valid preconditions When scenario Then expected result is achieved | E4: Preconditions | F4: Steps | G4: Test Data | H4: Expected Result | I4: Priority | J4: Type | K4: Automation Candidate | L4: Status | M4: Notes
A5: TC-HIS-001 | B5: History & Disputes | C5: Verify recent transactions list shows latest activity in reverse chronological order | D5: Given valid preconditions When verify recent transactions list shows latest activity in reverse chronological order Then expected result is achieved | E5: User has multiple completed transactions | F5: 1. Open transaction history | G5: Existing transaction history | H5: Transactions are listed newest first with visible status and amount | I5: High | J5: Positive | K5: Yes | L5: Not Run | M5: Core visibility
A6: TC-HIS-002 | B6: History & Disputes | C6: Verify transaction detail page shows accurate payment information | D6: Given valid preconditions When verify transaction detail page shows accurate payment information Then expected result is achieved | E6: At least one transaction exists | F6: 1. Open a completed payment or transfer | G6: Existing transaction | H6: Detail page shows correct amount, date/time, counterparty/merchant, reference, and status | I6: High | J6: Positive | K6: Yes | L6: Not Run | M6: Detail accuracy
A7: TC-HIS-003 | B7: History & Disputes | C7: Verify failed transaction is labelled correctly in history | D7: Given valid preconditions When verify failed transaction is labelled correctly in history Then expected result is achieved | E7: At least one failed transaction exists | F7: 1. Open history 2. Locate failed transaction | G7: Failed payment/transfer | H7: Failed item is clearly marked and does not appear as successful | I7: High | J7: Negative | K7: Yes | L7: Not Run | M7: Failure transparency
A8: TC-HIS-004 | B8: History & Disputes | C8: Verify pending transaction status updates correctly after backend completion | D8: Given valid preconditions When verify pending transaction status updates correctly after backend completion Then expected result is achieved | E8: Pending transaction exists | F8: 1. Open history during pending state 2. Refresh later | G8: Pending transaction | H8: Status eventually updates to correct final state | I8: High | J8: Regression | K8: Later | L8: Not Run | M8: Asynchronous update
A9: TC-HIS-005 | B9: History & Disputes | C9: Verify older transaction retrieval or message behaves per product policy | D9: Given valid preconditions When verify older transaction retrieval or message behaves per product policy Then expected result is achieved | E9: Transaction older than in-app threshold exists | F9: 1. Search/open older history period if supported | G9: Older transaction data | H9: App displays supported data or guidance according to retention policy | I9: Medium | J9: Regression | K9: Later | L9: Not Run | M9: Retention handling
A10: TC-HIS-006 | B10: History & Disputes | C10: Verify filtering by transaction type or date works correctly | D10: Given valid preconditions When verify filtering by transaction type or date works correctly Then expected result is achieved | E10: History filters are available | F10: 1. Apply transaction type/date filter 2. Review result set | G10: Date range/type filters | H10: Only matching transactions are shown | I10: Medium | J10: Positive | K10: Later | L10: Not Run | M10: Usability coverage
A11: TC-DSP-001 | B11: History & Disputes | C11: Verify user can start dispute/refund request from a completed transaction | D11: Given valid preconditions When verify user can start dispute/refund request from a completed transaction Then expected result is achieved | E11: Completed eligible transaction exists | F11: 1. Open transaction details 2. Start dispute/refund flow | G11: Completed transaction | H11: Dispute/refund request flow is available and opens correctly | I11: High | J11: Positive | K11: Later | L11: Not Run | M11: Support entry point
A12: TC-DSP-002 | B12: History & Disputes | C12: Verify dispute submission requires mandatory supporting details | D12: Given valid preconditions When verify dispute submission requires mandatory supporting details Then expected result is achieved | E12: Dispute flow is open | F12: 1. Leave mandatory dispute details blank 2. Submit | G12: Blank dispute details | H12: Submission is blocked with validation messages | I12: High | J12: Negative | K12: Later | L12: Not Run | M12: Case quality
A13: TC-DSP-003 | B13: History & Disputes | C13: Verify successful dispute submission creates reference/case ID | D13: Given valid preconditions When verify successful dispute submission creates reference/case id Then expected result is achieved | E13: Dispute flow is open | F13: 1. Complete dispute form with valid details 2. Submit | G13: Valid dispute data | H13: Case is submitted and reference ID/confirmation is displayed | I13: High | J13: Positive | K13: Later | L13: Not Run | M13: Case tracking
A14: TC-DSP-004 | B14: History & Disputes | C14: Verify suspicious/fraud transaction can be reported to support | D14: Given valid preconditions When verify suspicious/fraud transaction can be reported to support Then expected result is achieved | E14: Completed or suspicious transaction exists | F14: 1. Open report fraud/support flow 2. Submit case details | G14: Suspicious transaction details | H14: Fraud report is logged successfully | I14: High | J14: Security | K14: Later | L14: Not Run | M14: Fraud escalation

Sheet Security_Compliance
A1: Security and Compliance Test Cases
A2: Update the Status column during execution. Summary KPIs and counts refresh automatically.
A4: TC_ID | B4: Module | C4: Scenario | D4: Acceptance Criteria (BDD) Given valid preconditions When scenario Then expected result is achieved | E4: Preconditions | F4: Steps | G4: Test Data | H4: Expected Result | I4: Priority | J4: Type | K4: Automation Candidate | L4: Status | M4: Notes
A5: TC-SEC-001 | B5: Security & Compliance | C5: Verify session times out after configured inactivity period | D5: Given valid preconditions When verify session times out after configured inactivity period Then expected result is achieved | E5: User is logged in | F5: 1. Stay idle beyond timeout 2. Attempt to resume use | G5: Idle session | H5: Session expires and re-authentication is required | I5: High | J5: Security | K5: Yes | L5: Not Run | M5: Session control
A6: TC-SEC-002 | B6: Security & Compliance | C6: Verify sensitive actions require authentication or step-up validation | D6: Given valid preconditions When verify sensitive actions require authentication or step-up validation Then expected result is achieved | E6: Logged-in user is initiating transfer or payment | F6: 1. Start sensitive action 2. Proceed to final confirmation | G6: Valid payment/transfer | H6: Strong auth/PIN/OTP is required before completion | I6: Critical | J6: Security | K6: Yes | L6: Not Run | M6: Step-up auth
A7: TC-SEC-003 | B7: Security & Compliance | C7: Verify app masks sensitive user/payment details where appropriate | D7: Given valid preconditions When verify app masks sensitive user/payment details where appropriate Then expected result is achieved | E7: User is logged in | F7: 1. Open profile, history, and payment screens | G7: Existing user data | H7: Sensitive information is masked according to policy | I7: Medium | J7: Security | K7: Later | L7: Not Run | M7: Privacy UX
A8: TC-SEC-004 | B8: Security & Compliance | C8: Verify rooted/jailbroken/tampered device handling follows policy | D8: Given valid preconditions When verify rooted/jailbroken/tampered device handling follows policy Then expected result is achieved | E8: Test device is compromised or device check is simulated | F8: 1. Launch app on compromised/tampered environment | G8: Tampered device | H8: App warns, blocks, or restricts usage per policy | I8: High | J8: Security | K8: Later | L8: Not Run | M8: Device integrity
A9: TC-SEC-005 | B9: Security & Compliance | C9: Verify rapid repeated transactions trigger fraud/risk controls | D9: Given valid preconditions When verify rapid repeated transactions trigger fraud/risk controls Then expected result is achieved | E9: Verified user is logged in | F9: 1. Attempt multiple similar transactions rapidly | G9: Rapid repeated payment attempts | H9: Risk controls flag, throttle, or block suspicious pattern | I9: Critical | J9: Security | K9: Later | L9: Not Run | M9: Fraud detection
A10: TC-SEC-006 | B10: Security & Compliance | C10: Verify account freeze or hold blocks all outbound financial actions | D10: Given valid preconditions When verify account freeze or hold blocks all outbound financial actions Then expected result is achieved | E10: Account is on compliance hold/freeze | F10: 1. Attempt payment 2. Attempt transfer | G10: Frozen account | H10: All restricted outbound actions are blocked consistently | I10: Critical | J10: Negative | K10: Yes | L10: Not Run | M10: Compliance enforcement
A11: TC-SEC-007 | B11: Security & Compliance | C11: Verify audit evidence can be linked from requirement to test result | D11: Given valid preconditions When verify audit evidence can be linked from requirement to test result Then expected result is achieved | E11: Test execution artifacts and requirement IDs are available | F11: 1. Review requirement mapping 2. Review linked evidence | G11: Requirement IDs and screenshots/logs | H11: Requirement, test case, result, and evidence are traceable | I11: High | J11: Audit | K11: Later | L11: Not Run | M11: Release readiness
A12: TC-SEC-008 | B12: Security & Compliance | C12: Verify no production/cardholder data is used in AI-assisted test assets | D12: Given valid preconditions When verify no production/cardholder data is used in ai-assisted test assets Then expected result is achieved | E12: Approved AI-assisted testing workflow is available | F12: 1. Review generated test assets/prompts/data 2. Check sample data usage | G12: AI-generated test assets | H12: Only sanitized/non-production data is present | I12: Critical | J12: Compliance | K12: Later | L12: Not Run | M12: AI governance
A13: TC-SEC-009 | B13: Security & Compliance | C13: Verify app logs and client-side errors do not expose secrets | D13: Given valid preconditions When verify app logs and client-side errors do not expose secrets Then expected result is achieved | E13: Logging/diagnostic review is available | F13: 1. Trigger controlled error 2. Review app/client logs | G13: Controlled test error | H13: Logs do not expose secrets, tokens, or full sensitive values | I13: High | J13: Security | K13: Later | L13: Not Run | M13: Secure logging

Sheet End_to_End
A1: End-to-End Test Cases
A2: Update the Status column during execution. Summary KPIs and counts refresh automatically.
A4: TC_ID | B4: Module | C4: Scenario | D4: Acceptance Criteria (BDD) Given valid preconditions When scenario Then expected result is achieved | E4: Preconditions | F4: Steps | G4: Test Data | H4: Expected Result | I4: Priority | J4: Type | K4: Automation Candidate | L4: Status | M4: Notes
A5: TC-E2E-001 | B5: End-to-End | C5: Verify new verified user can complete full onboarding to first successful QR payment | D5: Given valid preconditions When verify new verified user can complete full onboarding to first successful qr payment Then expected result is achieved | E5: Fresh user and test merchant QR are available | F5: 1. Register new user 2. Complete verification 3. Log in 4. Scan valid QR 5. Confirm payment | G5: New user + valid merchant QR | H5: User completes onboarding and first QR payment successfully | I5: Critical | J5: Positive | K5: Later | L5: Not Run | M5: Flagship acceptance flow
A6: TC-E2E-002 | B6: End-to-End | C6: Verify returning user can complete successful transfer and see it in history | D6: Given valid preconditions When verify returning user can complete successful transfer and see it in history Then expected result is achieved | E6: Existing verified user with sufficient balance exists | F6: 1. Log in 2. Transfer to valid recipient 3. Open history | G6: Valid recipient and amount | H6: Transfer succeeds and appears correctly in history | I6: Critical | J6: Positive | K6: Yes | L6: Not Run | M6: Primary returning-user flow
A7: TC-E2E-003 | B7: End-to-End | C7: Verify local QR payment totals remain consistent across payment, wallet balance, and history | D7: Given valid preconditions When verify local qr payment totals remain consistent across payment, wallet balance, and history Then expected result is achieved | E7: Verified user with known starting balance exists | F7: 1. Capture starting balance 2. Complete QR payment 3. Check ending balance and history | G7: Valid QR and known amount | H7: Deduction amount matches payment and history record exactly | I7: Critical | J7: Regression | K7: Yes | L7: Not Run | M7: Financial integrity
A8: TC-E2E-004 | B8: End-to-End | C8: Verify duplicate-submit protection across QR payment under network delay | D8: Given valid preconditions When verify duplicate-submit protection across qr payment under network delay Then expected result is achieved | E8: Verified user is logged in and valid QR is available | F8: 1. Initiate payment 2. Cause delay 3. Retry/press confirm again | G8: Valid QR with induced delay | H8: Only one completed transaction exists end-to-end | I8: Critical | J8: Negative | K8: Later | L8: Not Run | M8: Idempotency across layers
A9: TC-E2E-005 | B9: End-to-End | C9: Verify frozen account cannot complete payment or transfer end-to-end | D9: Given valid preconditions When verify frozen account cannot complete payment or transfer end-to-end Then expected result is achieved | E9: Frozen account exists | F9: 1. Log in to frozen account 2. Attempt QR payment 3. Attempt transfer | G9: Frozen account | H9: Both flows are blocked and status messaging is consistent | I9: Critical | J9: Negative | K9: Yes | L9: Not Run | M9: Compliance gate
A10: TC-E2E-006 | B10: End-to-End | C10: Verify dispute can be raised for a completed QR payment end-to-end | D10: Given valid preconditions When verify dispute can be raised for a completed qr payment end-to-end Then expected result is achieved | E10: Completed eligible QR payment exists | F10: 1. Open history 2. Open transaction 3. Submit dispute | G10: Completed QR payment | H10: Dispute submission succeeds and case reference is generated | I10: High | J10: Positive | K10: Later | L10: Not Run | M10: Post-transaction support flow
